ravendb_test_driver/__init__.py
ravendb_test_driver/options.py
ravendb_test_driver/raven_test_driver.py
ravendb_test_driver-7.1.4.dist-info/METADATA
ravendb_test_driver-7.1.4.dist-info/WHEEL
ravendb_test_driver-7.1.4.dist-info/top_level.txt
ravendb_test_driver-7.1.4.dist-info/RECORD
