Metadata-Version: 2.1
Name: ravendb-test-driver
Version: 7.1.4
Summary: RavenDB package for writing integration tests against RavenDB server
Home-page: https://github.com/ravendb/ravendb-python-testdriver
Author: RavenDB
Author-email: support@ravendb.net
License: MIT
Keywords: ravendb,nosql,database,test,driver
Requires-Python: ~=3.9
Requires-Dist: ravendb-embedded==7.1.4
Requires-Dist: ravendb~=7.1.4
